SimpleCache2/CacheSystem.py
SimpleCache2/FileCache.py
SimpleCache2/MemoryCache.py
SimpleCache2/Settings.py
SimpleCache2/__init__.py
SimpleCache2/utils.py
SimpleCache2-1.2.1.dist-info/METADATA
SimpleCache2-1.2.1.dist-info/WHEEL
SimpleCache2-1.2.1.dist-info/top_level.txt
SimpleCache2-1.2.1.dist-info/RECORD
