Metadata-Version: 2.1
Name: SimpleCache2
Version: 1.2.1
Summary: Cache system for python
Home-page: https://github.com/traineratwot/SimpleCache2
Author: Traineratwot
Author-email: Traineratwot@yandex.ru
Classifier: Programming Language :: Python :: 3
Classifier: License :: OSI Approved :: MIT License
Classifier: Operating System :: OS Independent
